krita/__init__.py
krita/cli.py
krita/generator.py
krita/llm.py
krita/schema.py
krita/uploader.py
krita-0.1.6.dist-info/licenses/LICENSE
krita-0.1.6.dist-info/METADATA
krita-0.1.6.dist-info/WHEEL
krita-0.1.6.dist-info/entry_points.txt
krita-0.1.6.dist-info/top_level.txt
krita-0.1.6.dist-info/RECORD
