Metadata-Version: 2.4
Name: krita
Version: 0.1.6
Summary: Krita (कृत): Create synthetic datasets using LLMs from schemas
Author-email: Krita Team <krita@example.com>
License: MIT
Project-URL: Homepage, https://github.com/hemanth/krita
Project-URL: Repository, https://github.com/hemanth/krita.git
Project-URL: Issues, https://github.com/hemanth/krita/issues
Project-URL: Documentation, https://github.com/hemanth/krita#readme
Keywords: synthetic-data,llm,datasets,machine-learning,sanskrit,krita
Classifier: Development Status :: 3 - Alpha
Classifier: Intended Audience :: Developers
Classifier: License :: OSI Approved :: MIT License
Classifier: Programming Language :: Python :: 3
Classifier: Programming Language :: Python :: 3.8
Classifier: Programming Language :: Python :: 3.9
Classifier: Programming Language :: Python :: 3.10
Classifier: Programming Language :: Python :: 3.11
Classifier: Programming Language :: Python :: 3.12
Requires-Python: >=3.8
License-File: LICENSE
Requires-Dist: pydantic>=2.0.0
Requires-Dist: datasets>=2.0.0
Requires-Dist: huggingface-hub>=0.16.0
Requires-Dist: openai>=1.0.0
Requires-Dist: anthropic>=0.18.0
Requires-Dist: click>=8.0.0
Requires-Dist: pyyaml>=6.0
Requires-Dist: rich>=13.0.0
Requires-Dist: requests>=2.25.0
Provides-Extra: dev
Requires-Dist: pytest>=7.0.0; extra == "dev"
Requires-Dist: black>=23.0.0; extra == "dev"
Requires-Dist: isort>=5.0.0; extra == "dev"
Requires-Dist: mypy>=1.0.0; extra == "dev"
Requires-Dist: pre-commit>=3.0.0; extra == "dev"
Dynamic: license-file
